Metadata-Version: 2.1
Name: django-simple-notice
Version: 0.2.10
Summary: A very simple, yet powerful, Django notice application
Home-page: https://github.com/czp-first/django-simple-notice
Author: rey
Author-email: zpcao.first@google.com
License: MIT
Platform: UNKNOWN
Classifier: Environment :: Web Environment
Classifier: Intended Audience :: Developers
Classifier: License :: OSI Approved :: MIT License
Classifier: Operating System :: OS Independent
Classifier: Programming Language :: Python
Classifier: Programming Language :: Python :: 3.6
Classifier: Programming Language :: Python :: 3.7
Classifier: Programming Language :: Python :: 3.8
Classifier: Topic :: Security
Classifier: Topic :: Internet :: WWW/HTTP
Classifier: Framework :: Django
License-File: LICENSE
